vibe/__init__.py
vibe/whats_new.md
vibe/acp/__init__.py
vibe/acp/acp_agent_loop.py
vibe/acp/entrypoint.py
vibe/acp/utils.py
vibe/acp/tools/__init__.py
vibe/acp/tools/base.py
vibe/acp/tools/session_update.py
vibe/acp/tools/builtins/bash.py
vibe/acp/tools/builtins/read_file.py
vibe/acp/tools/builtins/search_replace.py
vibe/acp/tools/builtins/todo.py
vibe/acp/tools/builtins/write_file.py
vibe/cli/__init__.py
vibe/cli/cli.py
vibe/cli/clipboard.py
vibe/cli/commands.py
vibe/cli/entrypoint.py
vibe/cli/history_manager.py
vibe/cli/terminal_setup.py
vibe/cli/autocompletion/__init__.py
vibe/cli/autocompletion/base.py
vibe/cli/autocompletion/path_completion.py
vibe/cli/autocompletion/slash_command.py
vibe/cli/plan_offer/decide_plan_offer.py
vibe/cli/plan_offer/adapters/http_whoami_gateway.py
vibe/cli/plan_offer/ports/whoami_gateway.py
vibe/cli/textual_ui/__init__.py
vibe/cli/textual_ui/app.py
vibe/cli/textual_ui/app.tcss
vibe/cli/textual_ui/external_editor.py
vibe/cli/textual_ui/terminal_theme.py
vibe/cli/textual_ui/handlers/__init__.py
vibe/cli/textual_ui/handlers/event_handler.py
vibe/cli/textual_ui/widgets/__init__.py
vibe/cli/textual_ui/widgets/agent_indicator.py
vibe/cli/textual_ui/widgets/approval_app.py
vibe/cli/textual_ui/widgets/compact.py
vibe/cli/textual_ui/widgets/config_app.py
vibe/cli/textual_ui/widgets/context_progress.py
vibe/cli/textual_ui/widgets/loading.py
vibe/cli/textual_ui/widgets/messages.py
vibe/cli/textual_ui/widgets/no_markup_static.py
vibe/cli/textual_ui/widgets/path_display.py
vibe/cli/textual_ui/widgets/question_app.py
vibe/cli/textual_ui/widgets/spinner.py
vibe/cli/textual_ui/widgets/status_message.py
vibe/cli/textual_ui/widgets/tool_widgets.py
vibe/cli/textual_ui/widgets/tools.py
vibe/cli/textual_ui/widgets/utils.py
vibe/cli/textual_ui/widgets/welcome.py
vibe/cli/textual_ui/widgets/chat_input/__init__.py
vibe/cli/textual_ui/widgets/chat_input/body.py
vibe/cli/textual_ui/widgets/chat_input/completion_manager.py
mistral_vibe-2.0.2.dist-info/METADATA
mistral_vibe-2.0.2.dist-info/WHEEL
mistral_vibe-2.0.2.dist-info/entry_points.txt
mistral_vibe-2.0.2.dist-info/licenses/LICENSE
mistral_vibe-2.0.2.dist-info/RECORD
